{
  "title": "Birth Weight: MedlinePlus",
  "url": "https://medlineplus.gov/birthweight.html",
  "publisher": "medlineplus.gov",
  "date": "2026-01-28",
  "text": "eing born. A low birth weight means that the baby is less than 5 pounds, 8 ounces. A high birth weight means that the baby is more than 8 pounds, 13 ounces.\nWhat can cause low birth weight? \nA baby with a low birth weight can be born too small, too early ( premature ), or both. This can happen for many different reasons. They include:\nHealth problems in the pregnant parent \nTaking certain medicines during pregnancy \nSubstance use during pregnancy \nInfections during pregnancy \nBeing pregnant with multiple babies \nProblems with the placenta, the organ that brings oxygen and nutrients to the baby \nHaving small parents \nGenetic conditions in the baby \nBirth defects \nWhat problems can low birth weight cause? \nBabies with low birth weight may be more at risk of certain health problems. They include immediate problems, such as:\nBreathing problems \nInfections \nHypoglycemia (low blood sugar) \nJaundice \nTrouble keeping warm \nThere is also a higher risk of longer-term problems, including:\nDelayed motor and social development \nLearning disabilities \nCertain health conditions as an adult, such as heart disease , high blood pressure , diabetes , and obesity \nWhat can cause high birth weight? \nCauses of high birth weight can include:\nHaving big parents \nDiabetes in the pregnant parent \nCertain genetic conditions \nToo much weight gain during pregnancy \nWhat problems can high birth weight cause",
  "source_type": "library",
  "source_id": "medlineplus_gov_birthweight_html_988cd720bda3",
  "chunk_id": "chunk_002"
}
