{
  "title": "Human Papillomavirus (HPV) Infection - STI Treatment Guidelines",
  "url": "https://www.cdc.gov/std/treatment-guidelines/anogenital-warts.htm",
  "publisher": "cdc.gov",
  "date": "2026-01-28",
  "text": "nefit from an inspection of the anal canal by digital examination, standard anoscopy, or high-resolution anoscopy.\n&dagger; Might weaken condoms and vaginal diaphragms.\nImiquimod is a patient-applied, topically active immune enhancer that stimulates production of interferon and other cytokines. Imiquimod 5% cream should be applied once at bedtime, 3 times/week for up to 16 weeks ( 1217 ). Similarly, imiquimod 3.75% cream should be applied once at bedtime every night for up to 8 weeks ( 1218 ). With either formulation, the treatment area should be washed with soap and water 6&ndash;10 hours after the application. Local inflammatory reactions, including redness, irritation, induration, ulceration or erosion, and vesicles might occur with using imiquimod, and hypopigmentation has also been described ( 1219 ). Limited case reports demonstrate an association between treatment with imiquimod cream and worsened inflammatory or autoimmune skin diseases (e.g., psoriasis, vitiligo, or lichenoid dermatoses) ( 1220 &ndash; 1222 ). Data from studies of human participants are limited regarding use of imiquimod during pregnancy; however, animal data indicate that this therapy poses low risk ( 431 ).\nPodofilox (podophyllotoxin) is a patient-applied antimitotic drug that causes wart necrosis. Podofilox solution (using a cotton swab) or podofilox gel (using a finger) should be applied to anogeni",
  "source_type": "library",
  "source_id": "cdc_gov_std_treatment_guidelines_anogenital_warts_htm_94caa2dc4c09",
  "chunk_id": "chunk_006"
}
