{
  "title": "Breast abscess - NHS",
  "url": "https://www.nhs.uk/conditions/breast-abscess/",
  "publisher": "nhs.uk",
  "date": "2026-01-28",
  "text": "a breast abscess \nIf the GP thinks you have a breast abscess, they will refer you to hospital for an ultrasound scan of your breast to check for an abscess.\nThe GP may give you antibiotics first if they think you have a breast infection.\nImportant\nGo back to the GP if your symptoms do not start to improve within 2 days of starting antibiotics.\nTreatment for a breast abscess \nYou’ll need to go to hospital to have treatment for a breast abscess.\nTreatment involves the pus being drained from the abscess with either:\na needle – this might need to be done a few times and you may have to go back to hospital each time a small cut in your skin You'll be given a local anaesthetic before the pus is drained so you do not feel any pain. You can usually go home the same day and may be given antibiotics to take at home.\nThe abscess should heal completely in a few days or weeks.\nBreastfeeding during treatment\nContinue feeding with both breasts if you can. This will not harm your baby and can help your breast heal.\nTry expressing milk from your breasts with your hand or a breast pump if breastfeeding is too painful.\nCauses of a breast abscess \nA breast abscess can form if you have a breast infection (called mastitis ) and it's not treated quickly.\nYou're more likely to get mastitis if you are breastfeeding. You can get it if you're not breastfeeding, but this is less common.\nGetting treatment",
  "source_type": "library",
  "source_id": "nhs_uk_conditions_breast_abscess_c25bc1def66c",
  "chunk_id": "chunk_002"
}
