{
  "title": "Low blood pressure (hypotension) - NHS",
  "url": "https://www.nhs.uk/conditions/low-blood-pressure-hypotension/",
  "publisher": "nhs.uk",
  "date": "2026-01-28",
  "text": "﻿ \nLow blood pressure (hypotension)\n- NHS \nSkip to main content \nSearch the NHS website \nSearch \nHealth A to Z\nNHS services\nHealthy living\nMental health\nCare and support\nHome\nBrowse \nMore\nHome \nHealth A to Z \nConditions A to Z \nBack to \nConditions A to Z\nLow blood pressure (hypotension) \nLow blood pressure is a reading of less than 90/60mmHg. It does not always cause symptoms, but you may need treatment if it does. \nSymptoms of low blood pressure \nGet your blood pressure checked if you keep getting symptoms like:\nlightheadedness or dizziness feeling sick blurred vision generally feeling weak confusion fainting This might mean your blood pressure is too low.\nIf you get symptoms when you stand up or suddenly change position, you may have a type of low blood pressure called postural hypotension.\nNon-urgent advice: See a GP if:\nyou keep getting symptoms of low blood pressure such as dizziness and fainting \nHow to check your blood pressure \nYou can check your blood pressure:\nby asking if a pharmacist can do it by asking a practice nurse or GP to do it at home yourself using a home blood pressure monitor Low blood pressure is a measurement of less than 90/60mmHg.\nFind out about monitoring your blood pressure at home and choosing a monitor from Blood Pressure UK \nInformation: \nUnderstanding your blood pressure reading If you have a recent blood pressure reading use the NHS Check your",
  "source_type": "library",
  "source_id": "nhs_uk_conditions_low_blood_pressure_hypotension_0e280cda7e4b",
  "chunk_id": "chunk_001"
}
