{
  "title": "Lymphatic Diseases | Lymph Nodes | Swollen Glands | MedlinePlus",
  "url": "https://medlineplus.gov/lymphaticdiseases.html",
  "publisher": "medlineplus.gov",
  "date": "2026-01-28",
  "text": "for benign conditions: management of persistent inguinal lymphorrea. \nArticle: Percutaneous Thoracic Duct Externalization and Autotransfusion in Patients With Lymphatic Failure... \nArticle: Hypertension: a lymphatic disease? \nLymphatic Diseases -- see more articles \nReference Desk\nIntroduction to the Lymphatic System \n(National Cancer Institute) \nLymphatic System (For Parents) \n(Nemours Foundation) \nAlso in Spanish \nFind an Expert\nNational Cancer Institute \nAlso in Spanish \nNational Heart, Lung, and Blood Institute \nChildren\nChylous Ascites (For Parents) \n(Nemours Foundation) \nAlso in Spanish \nLymphatic Malformations (For Parents) \n(Nemours Foundation) \nAlso in Spanish \nTeenagers\nSpleen and Lymphatic System \n(Nemours Foundation) \nAlso in Spanish \nPatient Handouts\nCancer and lymph nodes \n(Medical Encyclopedia) \nAlso in Spanish \nCystic hygroma \n(Medical Encyclopedia) \nAlso in Spanish \nGroin lump \n(Medical Encyclopedia) \nAlso in Spanish \nLymph node biopsy \n(Medical Encyclopedia) \nAlso in Spanish \nLymph system \n(Medical Encyclopedia) \nAlso in Spanish \nLymphadenitis \n(Medical Encyclopedia) \nAlso in Spanish \nLymphangitis \n(Medical Encyclopedia) \nAlso in Spanish \nLymphofollicular hyperplasia \n(Medical Encyclopedia) \nAlso in Spanish \nNeck lump \n(Medical Encyclopedia) \nAlso in Spanish \nSwollen lymph nodes \n(Medical Encyclopedia) \nAlso in Spanish \nTopic Image \nMEDICAL ENCYCLOPEDIA \nArmp",
  "source_type": "library",
  "source_id": "medlineplus_gov_lymphaticdiseases_html_1fcf0a423afb",
  "chunk_id": "chunk_004"
}
