{
  "title": "State Vaccination Requirements | Vaccines &amp; Immunizations | CDC",
  "url": "https://www.cdc.gov/vaccines/php/requirements-laws/state-vaccination-requirements.html",
  "publisher": "cdc.gov",
  "date": "2026-01-28",
  "text": "ons to immunization. JAMA. 2000;284:3145-50. \nOmer SB, Enger KS, Moulton LH, Halsey NA, Stokley S, Salmon DA. Geographic clustering of nonmedical exemptions to school immunization requirements and associations with geographic clustering of pertussis. Am J Epidemiol. 2008;168:1389-96. \nOmer SB et al. Nonmedical exemptions to school immunization requirements: Secular trends and association of state policies with pertussis incidence. JAMA 2006;296:1757-1763. \nEase of obtaining a medical exemption and higher medical exemption rates \nStadlin S, Bednarczyk RA, Omer SB. Medical exemptions to school immunization requirements in the United States &mdash; association of state policies with medical exemption rates (2014-2011). JID 2012;206:989-992. \nChanging the ease of exemption requirements to decrease VPDs \nYang YT, Silverman RD. Legislative prescriptions for controlling nonmedical vaccine exemptions. JAMA Viewpoint. 2015;313:247-248. \nGostin LO. Law, ethics, and public health in the vaccination debates. Politics of the measles outbreak. JAMA 2015;313:1099-1100. \nStadlin S, Bednarczyk RA, Omer SB. Medical exemptions to school immunization requirements in the United States &ndash; association of state policies with medical exemption rates (2014-2011). JID 2012;206:989-992. \nOther \nOpel DJ, Omer SB. Measles, mandates, and making vaccination the default option. JAMA Pediatrics. 2015;16(4)",
  "source_type": "library",
  "source_id": "cdc_gov_vaccines_php_requirements_laws_state_vaccination_requirements_html_1a0adac02acd",
  "chunk_id": "chunk_006"
}
