{
  "title": "Interim Clinical Considerations for Use of Vaccine for Monkeypox Prevention in the United States | Monkeypox | CDC",
  "url": "https://www.cdc.gov/mpox/hcp/vaccine-considerations/vaccination-overview.html",
  "publisher": "cdc.gov",
  "date": "2026-01-28",
  "text": "tement (VIS) in Spanish \nVaccine Storage and Handling Toolkit \nJYNNEOS Standing Orders (Standard Regimen) \nFDA EUA Fact Sheet for Providers \nFDA EUA Fact Sheet for Patients and Caregivers \nFDA EUA Fact Sheet for Patients and Caregivers in Other Languages \nOn This Page \nVaccines \nRecommendations for use of JYNNEOS vaccine \nWhy people who recovered from monkeypox do not need JYNNEOS vaccine \nWhy boosters aren&rsquo;t currently recommended \nEvaluating patients \nPost-exposure prophylaxis (PEP) \nVaccination schedule \nDuration of immunity \nDosing intervals \nAdministration \nInterchangeability of dosing regimens \nCoadministration of JYNNEOS vaccine with other vaccines \nJYNNEOS vaccine administration considerations for specific populations \nPatient counseling \nContraindications and precautions \nReporting of adverse events \nResources \nSept. 5, 2025 \nSources \nPrint \nShare \nFacebook \nLinkedIn \nTwitter \nSyndicate \nContent Source: \nNational Center for Emerging and Zoonotic Infectious Diseases (NCEZID) \nFootnotes Research laboratory personnel are those who directly handle cultures or animals contaminated or infected with monkeypox virus (MPXV). Vaccination is not routinely recommended for clinical laboratory personnel who perform routine chemistry, hematology, and urinalysis testing, including for patients with suspected or confirmed MPXV infection, healthcare personnel who care for patients",
  "source_type": "library",
  "source_id": "cdc_gov_mpox_hcp_vaccine_considerations_vaccination_overview_html_2ed8aa52a8cc",
  "chunk_id": "chunk_028"
}
