{
  "title": "Depression: MedlinePlus",
  "url": "https://medlineplus.gov/depression.html",
  "publisher": "medlineplus.gov",
  "date": "2026-01-28",
  "text": "esearch \nClinical Trials \nJournal Articles \nResources \nFind an Expert \nFor You \nChildren \nTeenagers \nMen \nWomen \nOlder Adults \nPatient Handouts \nSummary \nWhat is depression? \nDepression is more than a feeling of being sad or irritable for a few days. It's a serious mood disorder . As one of the most common mental disorders in the United States, depression can affect how you think, feel, and your everyday life. You may not know why you feel this way, but even basic daily activities such as sleeping, eating, or working may become difficult. Depression often needs long-term treatment but getting help at the earliest sign of a problem can help manage your symptoms.\nWhat are the different types of depression? \nThe most common types of depression are major depression and persistent depressive disorder.\nMajor depression symptoms include a depressed mood or a loss of interest. Symptoms affect your daily activities and last for at least two weeks. \nPersistent depressive disorder (also called dysthymia or dysthymic disorder) has less severe depressive symptoms, but they last longer, usually for at least two years. \nOther types of depression can include:\nSeasonal affective disorder comes and goes with the seasons. It usually starts in late fall and early winter and goes away during the spring and summer. \nBipolar disorder is sometimes called manic depression. This mood disorder can cause",
  "source_type": "library",
  "source_id": "medlineplus_gov_depression_html_0d119a1ad6e9",
  "chunk_id": "chunk_002"
}
