{
  "title": "Obesity in Children: MedlinePlus",
  "url": "https://medlineplus.gov/obesityinchildren.html",
  "publisher": "medlineplus.gov",
  "date": "2026-01-28",
  "text": "s Health Topic \n(National Library of Medicine) \nAlso in Spanish \nLiving With\nEmotional Toll of Obesity \n(American Academy of Pediatrics) \nAlso in Spanish \nRelated Issues\nImpact of Childhood Obesity and Type2 Diabetes on Child Health \n(Nemours Foundation) \n- PDF \nGenetics\nProopiomelanocortin deficiency: MedlinePlus Genetics \n(National Library of Medicine) \nHealth Check Tools\nChild and Teen BMI Calculator \n(Centers for Disease Control and Prevention) \nAlso in Spanish \nStatistics and Research\nChildhood Obesity Facts \n(Centers for Disease Control and Prevention) \nFastStats: Obesity and Overweight \n(National Center for Health Statistics) \nOverweight and Obesity Statistics \n(National Institute of Diabetes and Digestive and Kidney Diseases) \nClinical Trials\nClinicalTrials.gov: Obesity in Children \n(National Library of Medicine) \nJournal Articles\nReferences and abstracts from MEDLINE/PubMed (National Library of Medicine) \nArticle: The effect of comprehensive intervention on family support and the mediating... \nArticle: Beyond Gestational Diabetes: Maternal and Offspring Health and Lifestyle 3 Years Postnatally... \nArticle: Effects of high-intensity interval training combined with dietary intervention on body... \nObesity in Children -- see more articles \nFind an Expert\nFind a Nutrition Expert \n(Academy of Nutrition and Dietetics) \nKidsHealth \n(Nemours Foundation) \nNational Institute o",
  "source_type": "library",
  "source_id": "medlineplus_gov_obesityinchildren_html_fed6e6f29c81",
  "chunk_id": "chunk_004"
}
