{
  "title": "Gestational DiabetesÂ | MedlinePlus",
  "url": "https://medlineplus.gov/diabetesandpregnancy.html",
  "publisher": "medlineplus.gov",
  "date": "2026-01-28",
  "text": "rces \nFind an Expert \nFor You \nPatient Handouts \nSummary \nWhat is diabetes? \nIf you have diabetes , your blood glucose , or blood sugar, levels are too high. Glucose comes from the foods you eat. A hormone called insulin helps the glucose get into your cells to give them energy. With type 1 diabetes , your body does not make insulin. With type 2 diabetes , your body does not make or use insulin well. Without enough insulin, the glucose stays in your blood.\nWhat is gestational diabetes? \nSome people already have diabetes before they get pregnant. But others may develop diabetes during pregnancy. This type of diabetes is called gestational diabetes. It usually develops around the 24th week of pregnancy. It happens when your body can't make the extra insulin it needs during pregnancy. Researchers think gestational diabetes is caused by the hormonal changes of pregnancy, along with genetic and lifestyle factors.\nWho is more likely to develop gestational diabetes? \nAnyone who is pregnant could develop gestational diabetes. But you are more likely to develop it if you:\nAre overweight or have obesity \nHave a family history of diabetes \nHad gestational diabetes in a previous pregnancy \nHave given birth to a baby weighing 9 pounds or more \nHave polycystic ovary syndrome (PCOS) \nAre African American, Hispanic/Latino, American Indian, Alaska Native, Native Hawaiian, or Pacific Islander pe",
  "source_type": "library",
  "source_id": "medlineplus_gov_diabetesandpregnancy_html_0fbae6a3cd89",
  "chunk_id": "chunk_002"
}
