{
  "title": "Emergency Department Survey of Vaccination Knowledge, Vaccination Coverage, and Willingness to Receive Vaccines in an Emergency Department Among Underserved Populations — Eight U",
  "url": "https://www.cdc.gov/mmwr/volumes/74/wr/mm7429a1.htm",
  "publisher": "cdc.gov",
  "date": "2026-01-28",
  "text": ".12 \n1.21\n(1.61&ndash;2.40) \n0.001 \n1.21\n(0.93&ndash;1.58) \n0.16 \nMixed \n1.13\n(0.80&ndash;1.60) \n0.48 \n1.03\n(0.71&ndash;1.48) \n0.88 \n1.92\n(1.03&ndash;4.01) \n0.06 \n1.38\n(0.71&ndash;2.94) \n0.37 \n1.42\n(0.98&ndash;2.05) \n0.06 \n1.42\n(0.97&ndash;2.08) \n0.07 \nOther \n1.61\n(1.20&ndash;2.15) \n0.001 \n1.21\n(0.87&ndash;1.65) \n0.27 \n1.58\n(0.96&ndash;2.75) \n0.08 \n1.24\n(0.72&ndash;2.27) \n0.46 \n1.09\n(0.85&ndash;1.60) \n0.36 \n1.09\n(0.77&ndash;1.55) \n0.61 \nPrimary language \nEnglish \n1.00\n(Ref) \n&mdash; \n1.00\n(Ref) \n&mdash; \n1.00\n(Ref) \n&mdash; \n1.00\n(Ref) \n&mdash; \n1.00\n(Ref) \n&mdash; \n1.00\n(Ref) \n&mdash; \nNot English \n2.44\n(2.05&ndash;2.92) \n<0.001 \n2.42\n(1.82&ndash;3.22) \n<0.001 \n1.18\n(0.85&ndash;1.66) \n0.34 \n1.42\n(0.83&ndash;2.48) \n0.30 \n2.75\n(2.28&ndash;3.33) \n<0.001 \n1.09\n(0.81&ndash;1.45) \n0.57 \nHave primary care physician \nYes \n1.00\n(Ref) \n&mdash; \n1.00\n(Ref) \n&mdash; \n1.00\n(Ref) \n&mdash; \n1.00\n(Ref) \n&mdash; \n1.00\n(Ref) \n&mdash; \n1.00\n(Ref) \n&mdash; \nNo \n2.45\n(2.06&ndash;2.93) \n<0.001 \n1.68\n(1.35&ndash;2.08) \n<0.001 \n3.57\n(2.26&ndash;6.02) \n<0.001 \n2.91\n(1.74&ndash;5.13) \n<0.001 \n1.29\n(1.08&ndash;1.54) \n0.006 \n0.83\n(0.66&ndash;1.05) \n0.12 \nHave health insurance \nYes \n1.00\n(Ref) \n&mdash; \n1.00\n(Ref) \n&mdash; \n1.00\n(Ref) \n&mdash; \n1.00\n(Ref) \n&mdash; \n1.00\n(Ref) \n&mdash; \n1.00\n(Ref) \n&mdash; \nNo \n2.42\n(1.84&ndash;3.20) \n<0.001 \n1.56\n(1.14&ndash;2.16) \n0.006 \n5.50\n(2.31&ndash;17.9) \n<0.001 \n3",
  "source_type": "library",
  "source_id": "cdc_gov_mmwr_volumes_74_wr_mm7429a1_htm_3fb3d62a8953",
  "chunk_id": "chunk_027"
}
