{
  "title": "Health Facilities: MedlinePlus",
  "url": "https://medlineplus.gov/healthfacilities.html",
  "publisher": "medlineplus.gov",
  "date": "2026-01-28",
  "text": "rences and abstracts from MEDLINE/PubMed (National Library of Medicine) \nArticle: Hospital Readmission Reduction Program Penalties for Hospitals With High Medicare Advantage... \nArticle: The mediating role of internal motivation on the relationship between ethical... \nArticle: Relationship between physical disability and satisfaction with medical care and health... \nHealth Facilities -- see more articles \nFind an Expert\nFind a Clinic \n(National Association of Free and Charitable Clinics) \nFindTreatment.gov \n(Substance Abuse and Mental Health Services Administration) \nAlso in Spanish \nMedicare: Find and Compare Health Care Providers \n(Centers for Medicare & Medicaid Services) \nAlso in Spanish \nChildren\nGoing to the Hospital \n(Nemours Foundation) \nAlso in Spanish \nPatient Handouts\nChoosing a skilled nursing and rehabilitation facility \n(Medical Encyclopedia) \nAlso in Spanish \nHow to choose the best hospital for surgery \n(Medical Encyclopedia) \nAlso in Spanish \nIsolation precautions \n(Medical Encyclopedia) \nAlso in Spanish \nLeaving the hospital - your discharge plan \n(Medical Encyclopedia) \nAlso in Spanish \nSkilled nursing or rehabilitation facilities \n(Medical Encyclopedia) \nAlso in Spanish \nTopic Image \nMEDICAL ENCYCLOPEDIA \nChoosing a skilled nursing and rehabilitation facility \nHow to choose the best hospital for surgery \nIsolation precautions \nLeaving the hospital - your disc",
  "source_type": "library",
  "source_id": "medlineplus_gov_healthfacilities_html_62544ade0b78",
  "chunk_id": "chunk_003"
}
