{
  "title": "Hyperglycemia | High Blood Sugar | Diabetes | MedlinePlus",
  "url": "https://medlineplus.gov/hyperglycemia.html",
  "publisher": "medlineplus.gov",
  "date": "2026-01-28",
  "text": "e team may make changes to your diabetes meal plan, physical activity plan, and/or diabetes medicines.\nIf you have severe hyperglycemia and are having symptoms of DKA, you will need treatment at the hospital. The treatment often includes I.V. (intravenous) fluids and insulin.\nCan hyperglycemia be prevented? \nIf you have diabetes, managing your diabetes can help prevent hyperglycemia. To manage your diabetes, it's important to:\nFollow your diabetes meal plan \nGet regular physical activity \nIf you need diabetes medicines, take them correctly \nRegularly check your blood glucose level \nGet regular checkups with your health care team \nStart Here\nHyperglycemia (High Blood Glucose) \n(American Diabetes Association) \nHyperglycemia in Diabetes \n(Mayo Foundation for Medical Education and Research) \nAlso in Spanish \nWhat Is High Blood Glucose? \n(Joslin Diabetes Center) \nDiagnosis and Tests\nA1C: MedlinePlus Health Topic \n(National Library of Medicine) \nAlso in Spanish \nBlood Glucose Test \n(National Library of Medicine) \nAlso in Spanish \nRelated Issues\nDiabetes and DKA (Ketoacidosis) \n(American Diabetes Association) \nDiabetic Ketoacidosis \n(Mayo Foundation for Medical Education and Research) \nClinical Trials\nClinicalTrials.gov: Hyperglycemia \n(National Institutes of Health) \nJournal Articles\nReferences and abstracts from MEDLINE/PubMed (National Library of Medicine) \nArticle: Purified Anthoc",
  "source_type": "library",
  "source_id": "medlineplus_gov_hyperglycemia_html_960fd100fd97",
  "chunk_id": "chunk_005"
}
