{
  "title": "Vulvovaginal Candidiasis - STI Treatment Guidelines",
  "url": "https://www.cdc.gov/std/treatment-guidelines/candidiasis.htm",
  "publisher": "cdc.gov",
  "date": "2026-01-28",
  "text": "onstrates budding yeasts, hyphae, or pseudohyphae, or a culture or other test yields a positive result for a yeast species. Candida vaginitis is associated with normal vaginal pH (<4.5). Use of 10% KOH in wet preparations improves the visualization of yeast and mycelia by disrupting cellular material that might obscure the yeast or pseudohyphae. Examination of a wet mount with KOH preparation should be performed for all women with symptoms or signs of VVC, and women with a positive result should be treated. For those with negative wet mounts but existing signs or symptoms, vaginal cultures for Candida should be considered. If Candida cultures cannot be performed for these women, empiric treatment can be considered. Identifying Candida by culture in the absence of symptoms or signs is not an indication for treatment because approximately 10%&ndash;20% of women harbor Candida species and other yeasts in the vagina. The majority of PCR tests for yeast are not FDA cleared, and providers who use these tests should be familiar with the performance characteristics of the specific test used. Yeast culture, which can identify a broad group of pathogenic yeasts, remains the reference standard for diagnosis.\nTreatment \nShort-course topical formulations (i.e., single dose and regimens of 1&ndash;3 days) effectively treat uncomplicated VVC. Treatment with azoles results in relief of symptom",
  "source_type": "library",
  "source_id": "cdc_gov_std_treatment_guidelines_candidiasis_htm_a93ac48140d4",
  "chunk_id": "chunk_003"
}
