{
  "title": "Strategies for Improving Antibiotic Use in Outpatient Hemodialysis Facilities | Antibiotic Prescribing and Use | CDC",
  "url": "https://www.cdc.gov/antibiotic-use/hcp/antibiotics-hemodialysis/index.html",
  "publisher": "cdc.gov",
  "date": "2026-01-28",
  "text": "g opportunities and strategies to optimize antibiotic use in outpatient hemodialysis facilities. \nDialysis Safety \nNephrologists Transforming Dialysis Safety Standardization of Blood Culture Collection for Patients Receiving In-Center Hemodialysis \nNHSN Dialysis Event \nOn This Page \nThe problem \nStrategies for outpatient dialysis facilities \nStrategies for any healthcare setting \nResources and tools \nSeptember 19, 2024 \nSources \nPrint \nShare \nFacebook \nLinkedIn \nTwitter \nSyndicate \nContent Source: \nNational Center for Emerging and Zoonotic Infectious Diseases (NCEZID) \nReferences Apata IW, Kabbani S, Neu AM, Kear TM, D'Agata EMC, Levenson DJ, Kliger AS, Hicks LA, Patel PR. Opportunities to Improve Antibiotic Prescribing in Outpatient Hemodialysis Facilities. AJKD . 2020. \nSnyder GM, Patel PR, Kallen AJ, Strom JA, Tucker JK, D'Agata EM. Antimicrobial use in outpatient hemodialysis units. Infect Control Hosp Epidemiol . 2013 Apr;34(4):349-57. doi: 10.1086/669869. Epub 2013 Feb 18. PMID: 23466906. \nD'Agata EMC, Lindberg CC, Lindberg CM, et al. The positive effects of an antimicrobial stewardship program targeting outpatient hemodialysis facilities. Infect Control Hosp Epidemiol. 2018;39(12):1400-1405. \nSources Apata IW, Kabbani S, Neu AM, Kear TM, D'Agata EMC, Levenson DJ, Kliger AS, Hicks LA, Patel PR. Opportunities to Improve Antibiotic Prescribing in Outpatient Hemodialysis Fac",
  "source_type": "library",
  "source_id": "cdc_gov_antibiotic_use_hcp_antibiotics_hemodialysis_index_html_c465b0f4fa98",
  "chunk_id": "chunk_008"
}
