{
  "title": "Tick Bites | Tickborne Disease | MedlinePlus",
  "url": "https://medlineplus.gov/tickbites.html",
  "publisher": "medlineplus.gov",
  "date": "2026-01-28",
  "text": "rents) \n(Nemours Foundation) \nAlso in Spanish \nTick Removal: A Step-by-Step Guide (For Parents) \n(Nemours Foundation) \nAlso in Spanish \nWhat to Do About Tick Bites (For Parents) \n(Nemours Foundation) \nAlso in Spanish \nPatient Handouts\nColorado tick fever \n(Medical Encyclopedia) \nAlso in Spanish \nEhrlichiosis \n(Medical Encyclopedia) \nAlso in Spanish \nRocky Mountain spotted fever \n(Medical Encyclopedia) \nAlso in Spanish \nTick bite \n(Medical Encyclopedia) \nAlso in Spanish \nTick paralysis \n(Medical Encyclopedia) \nAlso in Spanish \nTick removal \n(Medical Encyclopedia) \nAlso in Spanish \nTularemia \n(Medical Encyclopedia) \nAlso in Spanish \nTopic Image \nMEDICAL ENCYCLOPEDIA \nColorado tick fever \nEhrlichiosis \nRelapsing fever \nRocky Mountain spotted fever \nTick bite \nTick paralysis \nTick removal \nTularemia \nTularemia blood test \nRelated Health Topics \nInsect Bites and Stings \nLyme Disease \nNational Institutes of Health \nThe primary NIH organization for research on\nTick Bites is the\nNational Institute of Allergy and Infectious Diseases \nOther Languages \nFind health information in languages other than English on Tick Bites \nDisclaimers \nMedlinePlus links to health information from the National Institutes of Health and other federal government agencies. MedlinePlus also links to health information from non-government Web sites. See our disclaimer about external links and our quality guidelin",
  "source_type": "library",
  "source_id": "medlineplus_gov_tickbites_html_c71e01219953",
  "chunk_id": "chunk_007"
}
