{
  "title": "Tanning: MedlinePlus",
  "url": "https://medlineplus.gov/tanning.html",
  "publisher": "medlineplus.gov",
  "date": "2026-01-28",
  "text": "adult.\nSome research shows that frequent tanning may even be addictive. This can be dangerous because the more often you tan, the more damage you do to your skin.\nAre there safer ways to look tan? \nThere are other ways to look tan, but they are not all safe:\nTanning pills have a color additive that turns your skin orange after you take them. But they can be dangerous and are not approved by the Food and Drug Administration (FDA). \nSunless tanners have no known risk for skin cancer, but you do have to be careful. Most spray tans, lotions, and gels use DHA, a color additive that makes your skin look tan. DHA is considered safe for use on the outside of your body by the FDA. You need to make sure it doesn't get into your nose, eyes, or mouth. If you use a spray tan, be careful not to breathe in the spray. Also, remember that these \"tans\" do not protect you from UV rays when you go outside. \nLearn More\nMelanoma: MedlinePlus Genetics \n(National Library of Medicine) \nRisks of Tanning \n(Food and Drug Administration) \nSunless and Self-Tanning during Pregnancy \n(Nemours Foundation) \nAlso in Spanish \nTanning Products \n(Food and Drug Administration) \nJournal Articles\nReferences and abstracts from MEDLINE/PubMed (National Library of Medicine) \nArticle: Exploring factors associated with occupational health risk among tannery workers in... \nArticle: Integrated Risk Assessment of Tannery Effl",
  "source_type": "library",
  "source_id": "medlineplus_gov_tanning_html_894f7617ad14",
  "chunk_id": "chunk_005"
}
