{
  "title": "Update to CDC's Treatment Guidelines for Gonococcal Infection, 2020 | MMWR",
  "url": "https://www.cdc.gov/mmwr/volumes/69/wr/mm6950a6.htm?s_cid=mm6950a6_w",
  "publisher": "cdc.gov",
  "date": "2026-01-28",
  "text": "have completed and submitted the International Committee of Medical Journal Editors form for disclosure of potential conflicts of interest. Lindley Barbee reports a grant from SpeeDx and from Nabriva, personal fees from Nabriva, and nonfinancial support from Hologic, outside the submitted work. No other potential conflicts of interest were disclosed.\nTop \n* 2018 GISP sites: Albuquerque, New Mexico (1987&ndash;2018); Anchorage, Alaska (1987&ndash;2003, 2018); Atlanta, Georgia (1987&ndash;2018); Birmingham, Alabama (1987&ndash;2018); Boston, Massachusetts (1987&ndash;1992, 2014&ndash;2018); Buffalo, New York (2014&ndash;2018); Chicago, Illinois (1996&ndash;2018); Cleveland, Ohio (1991&ndash;2018); Columbus, Ohio (2012&ndash;2018); Dallas, Texas (1999&ndash;2018); Denver, Colorado (1987&ndash;2013, 2018); Greensboro, North Carolina (2002&ndash;2018); Honolulu, Hawaii (1987&ndash;2018); Indianapolis, Indiana (2013&ndash;2018); Jackson, Mississippi (2018); Kansas City, Missouri (1992&ndash;2001, 2007&ndash;2018); Las Vegas, Nevada (2002&ndash;2018); Los Angeles, California (2003&ndash;2018); Miami, Florida (1998&ndash;2013, 2018); Milwaukee, Wisconsin (2018); Minneapolis, Minnesota (1992&ndash;2018); New Orleans, Louisiana (1987&ndash;2018); New York, New York (2006&ndash;2018); Orange County, California (1991&ndash;2018); Phoenix, Arizona (1987&ndash;2018); Philadelphia, Pennsylvan",
  "source_type": "library",
  "source_id": "cdc_gov_mmwr_volumes_69_wr_mm6950a6_htm_7bfe1da4e1ad",
  "chunk_id": "chunk_016"
}
