{
  "title": "Blood Transfusion | Blood Donation | MedlinePlus",
  "url": "https://medlineplus.gov/bloodtransfusionanddonation.html",
  "publisher": "medlineplus.gov",
  "date": "2026-01-28",
  "text": "of American Pathologists) \nStatistics and Research\nBlood Facts and Statistics \n(American Red Cross) \nClinical Trials\nClinicalTrials.gov: Blood Donors \n(National Institutes of Health) \nClinicalTrials.gov: Blood Substitutes and Alternatives \n(National Institutes of Health) \nClinicalTrials.gov: Blood Transfusion \n(National Institutes of Health) \nClinicalTrials.gov: Transfusion Reaction \n(National Institutes of Health) \nJournal Articles\nReferences and abstracts from MEDLINE/PubMed (National Library of Medicine) \nArticle: Effectiveness of Closed Blood-Sampling Devices in Critically Ill Adults: A Feasibility... \nArticle: Correlation of plasma lipidomic profiles with cardiometabolic disease in transfusion-dependent thalassemia... \nArticle: Framework for the comprehensive screening for endocrine disorders in patients with... \nBlood Transfusion and Donation -- see more articles \nFind an Expert\nAmerican Red Cross \nAlso in Spanish \nNational Heart, Lung, and Blood Institute \nWhere to Donate Blood \n(Association for the Advancement of Blood & Biotherapies) \nTeenagers\nBlood Transfusions (For Teens) \n(Nemours Foundation) \nAlso in Spanish \nPatient Handouts\nBlood donation before surgery \n(Medical Encyclopedia) \nAlso in Spanish \nBlood transfusions \n(Medical Encyclopedia) \nAlso in Spanish \nTopic Image \nMEDICAL ENCYCLOPEDIA \nABO incompatibility \nBlood donation before surgery \nBlood transfusions \nEx",
  "source_type": "library",
  "source_id": "medlineplus_gov_bloodtransfusionanddonation_html_ad643b34ae1b",
  "chunk_id": "chunk_004"
}
