{
  "title": "Altered Immunocompetence | Vaccines &amp; Immunizations | CDC",
  "url": "https://www.cdc.gov/vaccines/hcp/imz-best-practices/altered-immunocompetence.html",
  "publisher": "cdc.gov",
  "date": "2026-01-28",
  "text": "delineates concentrations and proportions of lymphocyte subsets (i.e., B and T lymphocytes, CD4+ B lymphocytes versus CD8+ T lymphocytes), and tests that measure T-cell proliferation or function in response to specific or nonspecific stimuli (e.g., lymphocyte proliferation assays). 4 5 The ability to characterize a drug or disease condition as affecting cellular or humoral immunity is only the first step; using this information to draw inferences about whether particular vaccines are indicated or whether caution is advised with use of live or non-live vaccines is more complicated and might require consultation with an infectious diseases or immunology specialist.\nAltered Immunocompetence as an Indication to Receive a Vaccine Outside of Routinely Recommended Age Groups \nThis section describes situations in which vaccines are recommended outside of the routine-age-based recommendation because the risk for vaccine-preventable disease is increased due to altered immunocompetence. Persons with altered immunocompetence generally are recommended to receive polysaccharide-based vaccines (PCV13, PPSV23, and Hib), on the basis of increased risk for disease if the vaccine is withheld. For certain specific categories of altered immunocompetence, patients are also recommended to receive polysaccharide based vaccines (MenACWY, Hib-MenCY, and MPSV4).\nPneumococcal Vaccines \nTwo types of vacci",
  "source_type": "library",
  "source_id": "cdc_gov_vaccines_hcp_imz_best_practices_altered_immunocompetence_html_f30a0ba09054",
  "chunk_id": "chunk_006"
}
