{
  "title": "Core Elements of Hospital Diagnostic Excellence (DxEx) | Patient Safety | CDC",
  "url": "https://www.cdc.gov/patient-safety/hcp/hospital-dx-excellence/index.html",
  "publisher": "cdc.gov",
  "date": "2026-01-28",
  "text": "atment decisions. 104 \nEnsure that clinicians are provided clinical reasoning aids and other knowledge resources for diagnosis (e.g., CDC disease-specific guidance, specialty guidelines, testingwisely.com). \nProvide current best practices for understanding and communicating diagnostic uncertainty when discussing with patients 128 and during the transition of care. \nProvide education about cognitive biases and situations where biases based on patient characteristics (e.g., race) and co-occurring conditions are likely to be more common. \nImprove feedback by tracking patient outcomes and/or seeking feedback directly from peers or patients and families. 12 \nEncourage clinicians to implement reflective practices (e.g., periodically review patients' diagnostic outcomes and reflect on one's reasoning and decisions, consider using AHRQ's Calibrate Dx : A Resource to Improve Diagnostic Decisions). 5 \nOther examples \nConsider simulation-based training to improve feedback on diagnostic accuracy. 5 \nAs a part of clinical reasoning, educate clinicians about the value of evaluating and learning from diagnostic safety events. \nEducate providers how to leverage the knowledge and skills of other professionals on the care team when making a diagnosis. \nProvide education reflective practice skills, including a healthy skepticism of certainty in diagnosis and reconsidering diagnosis when patients",
  "source_type": "library",
  "source_id": "cdc_gov_patient_safety_hcp_hospital_dx_excellence_index_html_a9afc9e6d80c",
  "chunk_id": "chunk_039"
}
