{
  "title": "Ichthyosis - NHS",
  "url": "https://www.nhs.uk/conditions/ichthyosis/",
  "publisher": "nhs.uk",
  "date": "2026-01-28",
  "text": "3d0%26ot%3d0%26creative%3d%26ag%3d0%26hc%3d0%26pc%3d%26blackwhite%3d%26cutout%3d%26tbar%3d1%26et%3d0x000000000000000000000%26vp%3d0%26loc%3d0%26imgt%3d0%26dtfr%3d%26dtto%3d%26size%3d0xFF%26archive%3d1%26groupid%3d%26pseudoid%3d195878%26a%3d%26cdid%3d%26cdsrt%3d%26name%3d%26qn%3d%26apalib%3d%26apalic%3d%26lightbox%3d%26gname%3d%26gtype%3d%26xstx%3d0%26simid%3d%26saveQry%3d%26editorial%3d1%26nu%3d%26t%3d%26edoptin%3d%26customgeoip%3d%26cap%3d1%26cbstore%3d1%26vd%3d0%26lb%3d%26fi%3d2%26edrf%3d0%26ispremium%3d1%26flip%3d0%26pl%3d\nCredit: Science Photo Library: https://www.sciencephoto.com/media/1194989/view\nIchthyosis can sometimes have more severe symptoms, including:\nblistered skin a thin yellow, shiny layer on the skin at birth that dries out and flakes off hair loss tight skin which can make moving the affected area painful skin infections sweating less, which can lead to overheating problems with hearing or eyesight \nNon-urgent advice: See a GP if:\nyou or your child have symptoms of ichthyosis The GP may refer you to a skin specialist if they think you have ichthyosis.\nTreatments for ichthyosis \nMost types of ichthyosis cannot be cured, but there are treatments to help the symptoms.\nTreatments may include:\nmoisturising treatments ( emollients ), such as lotions, creams, ointments and bath oils peeling creams, such as salicylic acid A skin specialist will talk to you about the",
  "source_type": "library",
  "source_id": "nhs_uk_conditions_ichthyosis_fb8f69ed7104",
  "chunk_id": "chunk_002"
}
