{
  "title": "Rabies Cluster Among Steers on a Dairy Farm 芒聙聰 Minnesota, 2024 | MMWR",
  "url": "https://www.cdc.gov/mmwr/volumes/74/wr/mm7440a3.htm",
  "publisher": "cdc.gov",
  "date": "2026-01-28",
  "text": "ination \nVulnerability Disclosure Policy \nCDC Archive \nPublic Health Publications \nHHS.gov \nUSA.gov \nCONNECT WITH US \nFacebook \nTwitter \nInstagram \nLinkedIn \nYoutube \nPinterest \nSnapchat \nEmail \nLANGUAGES \nEspa脙卤ol \n莽鹿聛茅芦聰盲赂颅忙聳聡 \nTi谩潞驴ng Vi谩禄聡t \n铆聲聹锚碌颅矛聳麓 \nTagalog \n脨聽脩聝脩聛脩聛脨潞脨赂脨鹿 \n脴搂脵聞脴鹿脴卤脴篓脵聤脴漏 \nKrey脙虏l Ayisyen \nFran脙搂ais \nPolski \nPortugu脙陋s \nItaliano \nDeutsch \n忙聴楼忙聹卢猫陋聻 \n脵聛脴搂脴卤脴鲁脹聦 \nEnglish \nAccessibility \nExternal Links \nPrivacy \nWeb Policies \nFOIA \nOIG \nNo Fear Act \nNondiscrimination \nVulnerability Disclosure Policy \nCDC Archive \nPublic Health Publications \nHHS.gov \nUSA.gov \nSAS \nstats",
  "source_type": "library",
  "source_id": "cdc_gov_mmwr_volumes_74_wr_mm7440a3_htm_7a77be90b6cc",
  "chunk_id": "chunk_017"
}
