{
  "title": "Whooping Cough Vaccination | Whooping Cough | CDC",
  "url": "https://www.cdc.gov/pertussis/vaccines/index.html",
  "publisher": "cdc.gov",
  "date": "2026-01-28",
  "text": "h \nState mandate information \nChild care and elementary schools \nTdap booster requirements for secondary schools \nOn This Page \nOverview \nWhy getting vaccinated is important \nWho should and shouldn't get the vaccine \nHow well they work \nPossible side effects \nFinding and paying for vaccines \nResources \nDec. 2, 2025 \nSources \nPrint \nShare \nFacebook \nLinkedIn \nTwitter \nSyndicate \nContent Source: \nNational Center for Immunization and Respiratory Diseases ; Division of Bacterial Diseases \nWhooping Cough \nPertussis, also known as whooping cough, can cause serious illness in people of all ages but is most dangerous for babies.\nView All \nFor Everyone \nAbout \nSymptoms \nVaccination \nTreatment \nTrends \nHealth Care Providers \nClinical Overview \nClinical Features \nVaccine Recommendations \nView All \nPublic Health \nGuidance for Health Departments \nPostexposure Antimicrobial Prophylaxis \nLab Testing \nView All \nSign up for Email Updates \nContact Us \nContact Us \nCall 800-232-4636 \nContact CDC \nAbout CDC \nAbout CDC \nPressroom \nOrganization \nBudget & Funding \nCareers & Jobs \nPolicies \nAccessibility \nExternal Links \nPrivacy \nWeb Policies \nFOIA \nOIG \nNo Fear Act \nNondiscrimination \nVulnerability Disclosure Policy \nLanguages \nLanguages \nEspa횄짹ol \nLanguage Assistance \nEspa횄짹ol \n챌쨔혖챕짬혬채쨍짯챈혯혝 \nTi찼쨘쩔ng Vi찼쨩혝t \n챠혮혵챗쨉짯챙혯쨈 \nTagalog \n횖혻횗혘횗혖횗혖횖쨘횖쨍횖쨔 \n횠짠횢혙횠쨔횠짹횠짢횢혡횠짤 \nKrey횄짼l Ayisyen \nFran횄짠ais \nPolski \nPortug",
  "source_type": "library",
  "source_id": "cdc_gov_pertussis_vaccines_index_html_5e83f3121881",
  "chunk_id": "chunk_006"
}
