{
  "title": "Sexually transmitted infections (STIs) - NHS",
  "url": "https://www.nhs.uk/conditions/sexually-transmitted-infections-stis/",
  "publisher": "nhs.uk",
  "date": "2026-01-28",
  "text": "ore getting tested.\nFind out more about STI testing from Brook , including how long to wait before doing an STI test.\nNon-urgent advice: Go to a sexual health clinic if:\nyou think you may have an STI a sexual partner has symptoms of an STI you're worried after having sex without a condom you're pregnant with symptoms of an STI you're having casual sex without a condom with new partners – you may be at risk of HIV and other STIs Do not have sex, including oral sex, without using a condom until you've had a check-up or been tested.\nFind a sexual health clinic \nWhy you should go to a sexual health clinic You can see a GP, but they'll probably refer you to a sexual health clinic if they think you have an STI.\nYou do not usually need a GP referral or an appointment for a sexual health clinic, but contact the clinic first to check.\nDoctors and healthcare professionals are there to help you, so try not to feel uncomfortable about sharing information about your sexual activities or sexuality.\nYou do not need to give your real name or tell staff the name of your GP surgery if you do not want to. No information about your visit to the clinic will be shared with the GP or anyone else outside the clinic unless you ask for it to be.\nYou can ask to see a female or male doctor or nurse if you wish.\nWhat happens at a sexual health clinic \nIf you think you have a sexually transmitted infection",
  "source_type": "library",
  "source_id": "nhs_uk_conditions_sexually_transmitted_infections_stis_fb483114aa40",
  "chunk_id": "chunk_002"
}
