{
  "title": "Veterans and Military Health: MedlinePlus",
  "url": "https://medlineplus.gov/veteransandmilitaryhealth.html",
  "publisher": "medlineplus.gov",
  "date": "2026-01-28",
  "text": "ot wounds. \nLost limbs . \nWhat other special health problems do service members face? \nThere may also be a risk of health problems from exposure to environmental hazards, such as contaminated water, chemicals, infections, and burn pits. Sometimes the health problems caused by exposures don't develop until years later.\nSome service members experience military sexual trauma (MST). This includes sexual assault and sexual harassment.\nWhat mental health issues do service members and veterans face? \nBeing in combat and being separated from your family can be stressful. So can readjusting to civilian life after the military. All of this stress can put service members and veterans at risk for mental health problems, including:\nDepression \nPost-traumatic stress disorder (PTSD) \nAnxiety \nAlcohol and drug use disorders \nThere is also a risk of suicide . Veterans who are in crisis can get help from the Veteran's Crisis line by:\nCalling 988 and then pressing 1 \nTexting to 838255 \nChatting with them online \nWhat health care services are available to service members and veterans? \nThere are health care services especially for service members and veterans through:\nTRICARE, which is the Department of Defense's health care program. It has insurance plans and other services for uniformed service members, retirees, and their families around the world. \nThe Veterans Health Administration, which is",
  "source_type": "library",
  "source_id": "medlineplus_gov_veteransandmilitaryhealth_html_ffc830818080",
  "chunk_id": "chunk_003"
}
