{
  "title": "Health and social care delivery | Topic | NICE",
  "url": "https://www.nice.org.uk/guidance/health-and-social-care-delivery",
  "publisher": "org.uk",
  "date": "2026-01-28",
  "text": "Health and social care delivery | Topic | NICE \n-->\nHome \nNICE Guidance \nBrowse guidance by topic \nHealth and social care delivery \nAcute and critical care \nAdult&#x27;s social care \nAntimicrobial stewardship \nArtificial intelligence \nChildren&#x27;s social care \nDigital health \nEmergency care \nEnd of life care \nHealth inequalities \nJoint replacement \nMaternity services \nMedicines management \nMental health services \nMultiple long-term conditions \nOral and dental health \nOrgan and tissue transplantation \nPatient and service user care \nPrimary care management \nSafeguarding \nService transition \nStaffing \nSuicide prevention \nSurgical care \nTermination of pregnancy services \nAll categories \nConditions and diseases \nHealth and social care delivery \nHealth protection \nLifestyle and wellbeing \nPopulation groups \nSettings",
  "source_type": "library",
  "source_id": "org_uk_guidance_health_and_social_care_delivery_45a9ebe65667",
  "chunk_id": "chunk_001"
}
