{
  "title": "Myalgic Encephalomyelitis/Chronic Fatigue Syndrome | MedlinePlus",
  "url": "https://medlineplus.gov/myalgicencephalomyelitischronicfatiguesyndrome.html",
  "publisher": "medlineplus.gov",
  "date": "2026-01-28",
  "text": "n a plan. You should figure out which symptom causes you the most problems and try to treat that first. For example, if sleep problems affect you the most, you might first try using good sleep habits . If those do not help, you may need to take medicines or see a sleep specialist.\nStrategies such as learning new ways to manage activity can also be helpful. You need to make sure that you do not \"push and crash.\" This can happen when you feel better, do too much, and then get worse again.\nWhen you have ME/CFS, it can be hard to help develop a treatment plan. It can also be difficult to try to take care of yourself. So it's important that you have support from family members and friends.\nThere are also various resources and strategies that might be helpful to you, such as:\nGetting counseling to help you cope with the illness and its impact on your life. \nEating a healthy diet. \nNutritional supplements, if your provider suggests them. \nComplementary therapies such as meditation, gentle massage, or relaxation therapy. \nMake sure to talk to your provider before you try any new treatments. Some treatments that are promoted as cures for ME/CFS are unproven, often costly, and could be dangerous.\nCenters for Disease Control and Prevention\nStart Here\nChronic Fatigue Syndrome \n(Department of Health and Human Services, Office on Women&#x27;s Health) \nAlso in Spanish \nMyalgic Encephalomyelit",
  "source_type": "library",
  "source_id": "medlineplus_gov_myalgicencephalomyelitischronicfatiguesyndrome_html_0a08927992fa",
  "chunk_id": "chunk_005"
}
