{
  "title": "Nirsevimab Effectiveness Against Intensive Care Unit Admission for Respiratory Syncytial Virus in Infants — 24 States, December 2024–April 2025 | MMWR",
  "url": "https://www.cdc.gov/mmwr/volumes/74/wr/mm7437a1.htm",
  "publisher": "cdc.gov",
  "date": "2026-01-28",
  "text": "eron, MD 6 ; Jennifer E. Schuster, MD 7 ; Aline B. Maddux, MD 8 ; Kathleen Chiotos, MD 9 ; Katherine Irby, MD 10 ; Steven L. Shein, MD 11 ; Mary Allen Staat, MD 12 ; Lora M. Martin, MSN 13 ; Samina S. Bhumbra, MD 14 ; Ryan A. Nofziger, MD 15 ; Jigar C. Chauhan, MD 16 ,17 ; Danielle M. Zerr, MD 18 ,19 ; Shira J. Gertz, MD 20 ; Judith A. Guzman-Cottrill, DO 21 ; Michele Kong, MD 22 ; Janet R. Hume, MD 23 ; Bria M. Coates, MD 24 ; Kelly N. Michelson, MD 24 ; Emily R. Levy, MD 25 ; Tamara T. Bradford, MD 26 ,27 ; Stephanie P. Schwartz, MD 28 ; Tracie C. Walker, MD 28 ; Melissa S. Stockwell, MD 29 ,30 ; Austin Biggs, MD 31 ; Alexander H. Hogan, MD 32 ,33 ; Katherine Lindsey, MPH 1 ,34 ; Angela P. Campbell, MD 1 ,&dagger; ; Adrienne G. Randolph, MD 2 ,35 ,&dagger; ; Overcoming RSV Investigators ( View author affiliations )\nView suggested citation Summary \nWhat is already known about this topic? \nRespiratory syncytial virus (RSV) is a leading cause of infant hospitalization and intensive care unit (ICU) admission in the United States. Effectiveness of nirsevimab, a long-acting monoclonal antibody, has been established against RSV-associated lower respiratory tract infection and hospitalization among infants; nirsevimab is currently recommended by CDC to prevent severe RSV-related disease. Data are more limited regarding its effectiveness against RSV infection resulting in ICU admissio",
  "source_type": "library",
  "source_id": "cdc_gov_mmwr_volumes_74_wr_mm7437a1_htm_6678ac17ee58",
  "chunk_id": "chunk_002"
}
