{
  "title": "Mesothelioma - NHS",
  "url": "https://www.nhs.uk/conditions/mesothelioma/",
  "publisher": "nhs.uk",
  "date": "2026-01-28",
  "text": "﻿ \nMesothelioma\n- NHS \nSkip to main content \nSearch the NHS website \nSearch \nHealth A to Z\nNHS services\nHealthy living\nMental health\nCare and support\nHome\nBrowse \nMore\nHome \nHealth A to Z \nConditions A to Z \nBack to \nConditions A to Z\nMesothelioma \nMesothelioma is a type of cancer that develops in the lining that covers the outer surface of some of the body's organs. It's usually linked to asbestos exposure. \nMesothelioma mainly affects the lining of the lungs (pleural mesothelioma), although it can also affect the lining of the tummy (peritoneal mesothelioma), heart or testicles.\nMore than 2,700 people are diagnosed with mesothelioma each year in the UK. Most cases are diagnosed in people aged 75 and over, and men are affected more commonly than women.\nUnfortunately, it's not possible to cure mesothelioma, although treatment can help control the symptoms.\nSymptoms of mesothelioma \nThe symptoms of mesothelioma tend to develop gradually over time. They typically do not appear until several decades after exposure to asbestos.\nSymptoms of mesothelioma in the lining of the lungs include:\nchest pain shortness of breath fatigue (extreme tiredness) a high temperature and sweating, particularly at night a persistent  cough loss of appetite and unexplained weight loss clubbed (swollen) fingertips Symptoms of mesothelioma in the lining of the tummy include:\ntummy pain  or swelling feelin",
  "source_type": "library",
  "source_id": "nhs_uk_conditions_mesothelioma_079173730c20",
  "chunk_id": "chunk_001"
}
